{"tracedFiles":["index.html","js/applicationScript.js"],"id":"46c078f3-8ec3-4d1b-b594-192e1f9417ee","modelsToFile":{"8c46980d069375844ba19b821e3b3ea6":{"files":["index.html"]},"ab89b17face70cfd299e625d563d87a6":{"files":["index.html"]},"56f8d5454997e5fb637f14ef":{"files":["index.html","js/applicationScript.js"]},"ced0234567d1c6087cd52337":{"files":["js/applicationScript.js"]},"97dd593957161c29e6b7f595":{"files":["js/applicationScript.js"]},"4c449072103e76ac70ad5c37":{"files":["js/applicationScript.js"]},"a079ffc298fb6abe68d6fea0acb466b9":{"files":["index.html"]}}}